README.txt
setup.py
collective/__init__.py
collective.rtvideo.metacafe.egg-info/PKG-INFO
collective.rtvideo.metacafe.egg-info/SOURCES.txt
collective.rtvideo.metacafe.egg-info/dependency_links.txt
collective.rtvideo.metacafe.egg-info/entry_points.txt
collective.rtvideo.metacafe.egg-info/namespace_packages.txt
collective.rtvideo.metacafe.egg-info/not-zip-safe
collective.rtvideo.metacafe.egg-info/requires.txt
collective.rtvideo.metacafe.egg-info/top_level.txt
collective/rtvideo/__init__.py
collective/rtvideo/metacafe/__init__.py
collective/rtvideo/metacafe/configure.zcml
collective/rtvideo/metacafe/browser/__init__.py
collective/rtvideo/metacafe/browser/configure.zcml
collective/rtvideo/metacafe/browser/metacafeembedcode_template.pt
collective/rtvideo/metacafe/browser/videoembedcode.py
collective/rtvideo/metacafe/tests/__init__.py
collective/rtvideo/metacafe/tests/base.py
collective/rtvideo/metacafe/tests/test_videoembedcode.py
docs/HISTORY.txt
docs/INSTALL.txt
docs/LICENSE.GPL
docs/LICENSE.txt