Metadata-Version: 1.0
Name: collective.rtvideo.metacafe
Version: 0.1.0
Summary: The Metacafe Plone support for RedTurtle Video
Home-page: http://plone.org/products/redturtle.video
Author: RedTurtle Technology
Author-email: sviluppoplone@redturtle.net
License: GPL
Keywords: plone plonegov video embed metacafe
Platform: UNKNOWN
Classifier: Framework :: Plone
Classifier: Programming Language :: Python
Classifier: Topic :: Multimedia :: Video
Classifier: License :: OSI Approved :: GNU General Public License (GPL)
